range_digit/__init__.py
range_digit/py.typed
range_digit-0.3.1.dist-info/METADATA
range_digit-0.3.1.dist-info/WHEEL
range_digit-0.3.1.dist-info/licenses/LICENSE
range_digit-0.3.1.dist-info/RECORD
