Metadata-Version: 2.3
Name: range-digit
Version: 0.3.1
Summary: `range-digit` is library of decimal digit which has `low` and `sup`.
Project-URL: homepage, https://github.com/SaitoTsutomu/range-digit
Author-email: Saito Tsutomu <tsutomu7@hotmail.co.jp>
License: Apache-2.0
License-File: LICENSE
Classifier: Development Status :: 1 - Planning
Classifier: License :: OSI Approved :: Apache Software License
Classifier: Programming Language :: Python
Classifier: Topic :: Scientific/Engineering
Classifier: Topic :: Software Development
Requires-Python: >=3.12
